anthropic_token_counter-0.1.0.dist-info/licenses/LICENSE
atc/__init__.py
atc/cli.py
atc/config.py
atc/models.py
atc/token_counter.py
anthropic_token_counter-0.1.0.dist-info/METADATA
anthropic_token_counter-0.1.0.dist-info/WHEEL
anthropic_token_counter-0.1.0.dist-info/entry_points.txt
anthropic_token_counter-0.1.0.dist-info/top_level.txt
anthropic_token_counter-0.1.0.dist-info/RECORD
