Metadata-Version: 2.4
Name: anthropic-token-counter
Version: 0.1.0
Summary: Anthropic Tokens Counter - count tokens for Claude models
Author-email: weirdgiraffe <giraffe@cyberzoo.xyz>
License: MIT
Classifier: Development Status :: 3 - Alpha
Classifier: Intended Audience :: Developers
Classifier: License :: OSI Approved :: MIT License
Classifier: Operating System :: OS Independent
Classifier: Programming Language :: Python :: 3
Classifier: Programming Language :: Python :: 3.8
Classifier: Programming Language :: Python :: 3.9
Classifier: Programming Language :: Python :: 3.10
Classifier: Programming Language :: Python :: 3.11
Classifier: Programming Language :: Python :: 3.12
Requires-Python: >=3.8
License-File: LICENSE
Requires-Dist: anthropic>=0.8.0
Dynamic: license-file
